mcp_weather_http_sxw/__init__.py
mcp_weather_http_sxw/__main__.py
mcp_weather_http_sxw/server.py
mcp_streamable_weather_sxw-0.1.3.dist-info/METADATA
mcp_streamable_weather_sxw-0.1.3.dist-info/WHEEL
mcp_streamable_weather_sxw-0.1.3.dist-info/entry_points.txt
mcp_streamable_weather_sxw-0.1.3.dist-info/top_level.txt
mcp_streamable_weather_sxw-0.1.3.dist-info/RECORD
