Metadata-Version: 2.4
Name: mcp-streamable-weather-sxw
Version: 0.1.3
Summary: 输入心知天气-API-KEY，获取实时天气信息。
Requires-Python: >=3.12
Requires-Dist: mcp>=1.9.4
Requires-Dist: requests>=2.32.4
